ipars/CsvManagerCode.py
ipars/JsonManagerCode.py
ipars/ParsManagerCode.py
ipars/ProgressBarCode.py
ipars/TimerManagerCode.py
ipars/ZipManagerCode.py
ipars/__init__.py
ipars-3.9.2.dist-info/licenses/LICENSE
ipars-3.9.2.dist-info/METADATA
ipars-3.9.2.dist-info/WHEEL
ipars-3.9.2.dist-info/top_level.txt
ipars-3.9.2.dist-info/RECORD
