Metadata-Version: 2.4
Name: ipars
Version: 3.9.2
Summary: Библиотека для работы с файлами во время парсинга
Home-page: https://iliamiheev.github.io/ipars-doc/#/./home
Author: Ilia Miheev
Author-email: statute-wasp-frisk@duck.com
License: MIT
Project-URL: Bug Reports, https://github.com/IliaMiheev/ipars/issues
Project-URL: Source, https://github.com/IliaMiheev/ipars
Keywords: ipars,ипарс,парсинг,скрапинг,parsing,scraping,bs4,beautifulsoup4
License-File: LICENSE
Requires-Dist: requests
Requires-Dist: selenium
Requires-Dist: lxml
Requires-Dist: bs4
Requires-Dist: progress
Requires-Dist: random_user_agent
Requires-Dist: cerberus
Dynamic: author
Dynamic: author-email
Dynamic: description
Dynamic: description-content-type
Dynamic: home-page
Dynamic: keywords
Dynamic: license
Dynamic: license-file
Dynamic: project-url
Dynamic: requires-dist
Dynamic: summary
